<fr>
<string id=" is member of"> est membre de</string>
<string id=" is visible by groups"> est visualisable par les groupes</string>
<string id="---- Home page articles ----">---- Articles affichés sur la page d'accueil ----</string>
<string id="---- Proposed Home articles ----">---- Articles proposés pour la page d'accueil ----</string>
<string id="A file with the same name already exists">Il existe déjà un fichier portant ce nom</string>
<string id="A new article is proposed for home page(s)">Un nouveau article est proposé pour les pages d'accueil</string>
<string id="A new article is waiting for you">Un nouvel article vous attend</string>
<string id="A new comment is waiting for you">Il y a un commentaire en attente pour vous</string>
<string id="A new file has been uploaded">Un nouveau fichier a été chargé</string>
<string id="A new file is waiting for you">Il y a un fichier en attente</string>
<string id="A new post has been registered on forum">Une nouvelle contribution a été enregistré dans le forum</string>
<string id="A new post has been registered on thread">Une nouvelle contribution a été ajoutée au sujet de discussion</string>
<string id="About your article">Au sujet de votre article</string>
<string id="About your comment">A propos de votre commentaire</string>
<string id="Accepted">Accepté</string>
<string id="Acces denied">Accès refusé</string>
<string id="Acces">Accès</string>
<string id="Access denied">Accès refusé</string>
<string id="Access method">Méthode d'accès</string>
<string id="Access to Add-on">Accès au module</string>
<string id="Access">Accès</string>
<string id="Account confirmed ?">Compte confirmé ?</string>
<string id="Account disabled ?">Compte désactivé ?</string>
<string id="Accounts">Comptes</string>
<string id="Action">Action</string>
<string id="Activate Registration">Activer l'inscription</string>
<string id="Active">Active</string>
<string id="Add Account">Ajouter le compte</string>
<string id="Add Article">Ajouter un article</string>
<string id="Add Category">Ajouter une catégorie</string>
<string id="Add Comment">Ajouter un commentaire</string>
<string id="Add Contact">Ajouter un contact</string>
<string id="Add Domain">Ajouter le domaine</string>
<string id="Add Event">Ajouter un événement</string>
<string id="Add Group">Ajouter un groupe</string>
<string id="Add Question">Ajouter une question</string>
<string id="Add Resource">Ajouter une ressource</string>
<string id="Add Signature">Ajouter une signature</string>
<string id="Add a new faq">Ajouter une nouvelle faq</string>
<string id="Add a new folder">Ajouter un répertoire</string>
<string id="Add a new forum">Ajouter un forum</string>
<string id="Add account">Ajouter un compte</string>
<string id="Add article">Ajouter un article</string>
<string id="Add comment">Ajouter un commentaire</string>
<string id="Add entry to">Ajouter une entrée à</string>
<string id="Add new contact">Ajouter un contact</string>
<string id="Add new database directory">Ajouter un annuaire base de données</string>
<string id="Add new ldap directory">Ajouter un annuaire ldap</string>
<string id="Add question">Ajouter une question</string>
<string id="Add to contacts">Ajouter aux contacts</string>
<string id="Add to registered users home page">Proposer pour la page d'accueil privée</string>
<string id="Add to unregistered users home page">Proposer pour la page d'accueil publique</string>
<string id="Add user">Ajouter un utilisateur</string>
<string id="Add users">Ajouter des utilisateurs</string>
<string id="Add vacation type">Ajouter un type de congé</string>
<string id="Add vacation type's collection">Ajouter une régime de congé</string>
<string id="Add">Ajouter</string>
<string id="Add-ons list">Liste des modules</string>
<string id="Add-ons">Modules</string>
<string id="Additional detailed information ">Supplément d'information </string>
<string id="Additional information">Supplément d'information</string>
<string id="Administration">Administration</string>
<string id="Administrators">Administrateurs</string>
<string id="Afternoon">Après-midi</string>
<string id="Alignment">Alignement</string>
<string id="All collections">Tout régime</string>
<string id="All day">Toute la journée</string>
<string id="All">Tous</string>
<string id="Allocate vacation rights">Allouer des droits de congé</string>
<string id="Allow duplicates to be created">Permettre de créer les doublons</string>
<string id="Allowed">Alloué</string>
<string id="An article has been modified">Un article a été modifié</string>
<string id="An article has been published">Un article a été publié</string>
<string id="And / Or">Et / Oo</string>
<string id="Anonymous">Anonyme</string>
<string id="Approbation schema for articles">Schéma d'approbation pour les articles</string>
<string id="Approbation schema for comments">Schéma d'approbation pour les commentaires</string>
<string id="Approbation schema">Schéma d'approbation</string>
<string id="Approbations">Approbations</string>
<string id="Approved vacation request">Demande de congé approuvé</string>
<string id="Approver">Approbateur</string>
<string id="April">Avril</string>
<string id="Archive selected articles">Archiver les articles sélectionnés</string>
<string id="Archives">Archives</string>
<string id="Are you sure you want to delete the article">Etes-vous certain de vouloir supprimer l'article</string>
<string id="Are you sure you want to delete this approval schema">Etes-vous sûr de voumoir supprimer ce schéma d'approbation</string>
<string id="Are you sure you want to delete this calendar category">Etes-vous certain de vouloir supprimer cette catégorie d'agenda</string>
<string id="Are you sure you want to delete this calendar resource">Etes-vous certain de vouloir supprimer cette ressource</string>
<string id="Are you sure you want to delete this comment">Etes-vous certain de vouloir supprimer ce commentaire</string>
<string id="Are you sure you want to delete this directory">Etes vous sûr de vouloir supprimer cet annuaire</string>
<string id="Are you sure you want to delete this event">Etes-vous certain de vouloir détruire cet événement</string>
<string id="Are you sure you want to delete this faq">Etes-vous certain de bien vouloir supprimer cette FAQ</string>
<string id="Are you sure you want to delete this folder">Etes-vous sûr de vouloir supprimer ce répertoire</string>
<string id="Are you sure you want to delete this forum">Etes-vous certain de vouloir détruire ce forum</string>
<string id="Are you sure you want to delete this group">Etes-vous certain de vouloir détruire ce groupe</string>
<string id="Are you sure you want to delete this mail account">Etes-vous certain de vouloir supprimer ce compte de messagerie</string>
<string id="Are you sure you want to delete this mail domain">Etes-vous certain de vouloir supprimer ce domaine de messagerie</string>
<string id="Are you sure you want to delete this question">Etes-vous certain de vouloir supprimer cette question</string>
<string id="Are you sure you want to delete this section">Etes-vous certain de vouloir supprimer cette section</string>
<string id="Are you sure you want to delete this site">Etes-vous certain de vouloir supprimer ce site</string>
<string id="Are you sure you want to delete this status">Etes-vous certain de vouloir supprimer cet état</string>
<string id="Are you sure you want to delete this thread">Etes-vous certain de bien vouloir détruire ce sujet de discussion</string>
<string id="Are you sure you want to delete this topic category">Etes-vous certain de vouloir supprimer cette catégorie de thèmes d'articles</string>
<string id="Are you sure you want to delete this topic">Etes-vous certain de vouloir supprimer ce thème d'articles</string>
<string id="Are you sure you want to delete this user">Etes-vous certain de vouloir détruire cet utilisateur</string>
<string id="Are you sure you want to delete this vacation">Etes-vous certain de vouloir détruire ce type de congés</string>
<string id="Are you sure you want to delete those articles">Etes-vous certain de vouloir supprimer ces articles</string>
<string id="Are you sure you want to delete those contacts">Etes-vous certain de vouloir supprimer ces contacts</string>
<string id="Are you sure you want to delete those members">Etes-vous certain de vouloir supprimer ces utilisateurs</string>
<string id="Are you sure you want to empty this directory">Vous êtes sûr de vouloir vider cet annuaire</string>
<string id="Are you sure you want to remove the requests which finish before the following date ">Etes-vous sûr de vouloir supprimer les demandes dont la date de fin est avant la date suivante </string>
<string id="Are you sure you want to remove this request">Etes-vous sûr de vouloir supprimer cette demande de congé</string>
<string id="Are you sure you want to remove those users">Vous êtes sûr de vouloir supprimer ces utilisateurs</string>
<string id="Article">Article</string>
<string id="Article(s)">Article(s)</string>
<string id="Articles">Articles</string>
<string id="At least one">Au moins un</string>
<string id="Attachments">Pièces jointes</string>
<string id="August">Août</string>
<string id="Author">Auteur</string>
<string id="Available domains list">Liste des domaines disponibles</string>
<string id="Back to top">Haut</string>
<string id="Balance">Solde</string>
<string id="BaseDN">BaseDN</string>
<string id="Bcc">Bcc</string>
<string id="Begin date must be less than end date">La date de début doit être inférieure à la date de fin</string>
<string id="Begin date">Date de début</string>
<string id="Begin">Début</string>
<string id="Beneficiaries">Bénéficiaires</string>
<string id="Body">Corps</string>
<string id="Browse">Lister</string>
<string id="Business Address">Adresse prof.</string>
<string id="Business Tel">Tél. prof.</string>
<string id="By">Par</string>
<string id="Bytes">Octets</string>

<string id="Calendar Options">Options de l'Agenda</string>
<string id="Calendar access has been updated">L'agenda a été mis à jour</string>
<string id="Calendar categories list">Liste des catégories</string>
<string id="Calendar default view">Vue par défaut du calendrier</string>
<string id="Calendar resources list">Liste des ressources</string>
<string id="Calendar">Agenda</string>
<string id="Can user change password ?">L'utilisateur peut-il changer le mot de passe ?</string>
<string id="Can't create directory: ">Impossible de créer le répertoire: </string>
<string id="Can't delete this vacation right. It's used elsewhere">Impossible de supprimer ce droit de congé. Il est utilisé ailleurs</string>
<string id="Cancel">Annuler</string>
<string id="Cannot create temporary file">Impossible de créer un fichier temporaire</string>
<string id="Cannot open file for writing">Vous n'avez pas l'autorité d'écrire dans ce fichier</string>
<string id="Cannot paste file">Impossible de copier le fichier</string>
<string id="Cannot remove directory">Impossible de supprimer le répertoire</string>
<string id="Cannot rename directory">Impossible de renommer le répertoire</string>
<string id="Cannot upload file">Le fichier ne peut être chargé</string>
<string id="Categories">Catégories</string>
<string id="Category">Catégorie</string>
<string id="Cc">Cc</string>
<string id="Change password">Modifier le mot de passe</string>
<string id="Change user info">Changer les infos utilisateur</string>
<string id="Check all mails">Sélectionne tous les messages</string>
<string id="Check all">Sélectionner tout</string>
<string id="Click on this image to archive selected articles">Cliquer sur cette image pour archiver les articles sélectionnés</string>
<string id="Click on this image to delete selected articles">Cliquez sur cette image afin de supprimer les articles séléctionnés</string>
<string id="Click on this image to make selected articles available to registered users home page">Cliquez sur cette image afin de proposer les articles séléctionnés pour la page d'accueil privée</string>
<string id="Click on this image to make selected articles available to unregistered users home page">Cliquez sur cette image afin de proposer les articles séléctionnés pour la page d'accueil publique</string>
<string id="Click on this image to move out selected articles from archive">Cliquer sur cette image pour déplacer les articles sélectionnés des archives</string>
<string id="Close right">Droit fermé</string>
<string id="Close thread">Clore le sujet</string>
<string id="Close">Fermer</string>
<string id="Closed rights">Droits fermés</string>
<string id="Closed threads">Sujets fermés</string>
<string id="Closed">Sujets fermés</string>
<string id="Collection">Régime</string>
<string id="Collections">Régimes</string>
<string id="Color">Couleur</string>
<string id="Columns">Colonnes</string>
<string id="Comma">Virgule</string>
<string id="Comment">Commentaire</string>
<string id="Comment(s)">Commentaire(s)</string>
<string id="Comments">Commentaires</string>
<string id="Compagny">Société</string>
<string id="Compose">Ecrire</string>
<string id="Confirm vacation">Confirmer la demande de congé</string>
<string id="Confirm">Confirmer</string>
<string id="Consultation">Consultation</string>
<string id="Consumed">Consommé</string>
<string id="Contact">Contact</string>
<string id="Contacts list">Liste des contacts</string>
<string id="Contacts">Contacts</string>
<string id="Content">Contenu</string>
<string id="Create Calendar resource">Créer un agenda pour une ressource</string>
<string id="Create a calendar category">Créer une catégorie</string>
<string id="Create a global mail domain">Créer un domaine</string>
<string id="Create a group mail domain">Déclarer un nouveau domaine</string>
<string id="Create a group">Créer un groupe</string>
<string id="Create a note">Créer une note</string>
<string id="Create a private mail domain">Créer un domaine privé</string>
<string id="Create a topic category">Créer une catégorie de thèmes d'articles</string>
<string id="Create a user">Créer un utilisateur</string>
<string id="Create contact">Créer un contact</string>
<string id="Create new topic">Créer un nouveau thème d'articles</string>
<string id="Create section">Créer une section</string>
<string id="Create site">Créer un site</string>
<string id="Create">Créer</string>
<string id="Created">Crée</string>
<string id="Creation and modification">Création et modification</string>
<string id="Customize home pages ( Registered and unregistered users )">Personnaliser les pages d'accueil ( publique et privée )</string>
<string id="Cut">Couper</string>
<string id="Database Directory">Annuaire Base de données</string>
<string id="Database server version">Version de la base de données</string>
<string id="Databases Directories list">Liste des annuaires ( base de données )</string>
<string id="Date">Date</string>
<string id="Day">Jour</string>
<string id="Day(s)">Jour(s)</string>
<string id="Days must be multiple of 0.5">Le nombre de jours doit être multiple de 0.5</string>
<string id="Days">Jours</string>
<string id="December">Décembre</string>
<string id="Decimal separator">Séparateur décimal</string>
<string id="Default Value">Valeur par défaut</string>
<string id="Default days number">Nombre de jours par défaut</string>
<string id="Default group for confirmed users">Groupe par défaut des utlisateurs confirmés</string>
<string id="Default number of messages to display per screen">Nombre de messages par page affichés dans la liste</string>
<string id="Default password">Mot de passe par défaut</string>
<string id="Delete Comment">Supprimer le commentaire</string>
<string id="Delete Contacts">Supprimer les contacts</string>
<string id="Delete Database Directory">Supprimer l'annuaire</string>
<string id="Delete FAQ">Supprimer la FAQ</string>
<string id="Delete a forum">Supprimer un forum</string>
<string id="Delete a topic">Effacer un thème d'articles</string>
<string id="Delete a user">Supprimer un utilisateur</string>
<string id="Delete account">Supprimer ce compte</string>
<string id="Delete article">Supprimer l'article</string>
<string id="Delete articles">Supprimer ces articles</string>
<string id="Delete calendar category">Supprimer la catégorie d'agenda</string>
<string id="Delete calendar event">Supprimer un évènement</string>
<string id="Delete calendar resource">Supprimer une ressource</string>
<string id="Delete contact">Supprimer le contact</string>
<string id="Delete directory">Supprimer l'annuaire</string>
<string id="Delete doamain mail">Supprimer ce domaine de messagerie</string>
<string id="Delete folder">Suuprimer le répertoire</string>
<string id="Delete group">Supprimer un groupe</string>
<string id="Delete group's members">Supprimer les utilisateurs du groupe</string>
<string id="Delete question">Supprimer la question</string>
<string id="Delete request vacation">Supprimer une demande de congé</string>
<string id="Delete requests vacations">Supprimer les demandes de congés</string>
<string id="Delete schema">Supprimer le schéma</string>
<string id="Delete thread">Supprimer le sujet</string>
<string id="Delete topic category">Supprimer une catégorie de thèmes d'articles</string>
<string id="Delete users">Supprimer ces utilisateurs</string>
<string id="Delete vacation">Supprimer la demande de congés</string>
<string id="Delete">Supprimer</string>
<string id="Description">Description</string>
<string id="Directories">Annuaires</string>
<string id="Directory">Répertoire</string>
<string id="Disable">Désactiver</string>
<string id="Disabled">Désactivé</string>
<string id="Display">Affichage</string>
<string id="Do not import duplicates">Ne pas importer les doublons</string>
<string id="Document Tag">Balise du document</string>
<string id="Domain">Domaine</string>
<string id="Domains">Domaines</string>
<string id="Download">Télécharger</string>
<string id="ERROR - Nickname is required">ERREUR - L'identifiant est nécessaire</string>
<string id="ERROR">ERREUR</string>
<string id="ERROR: End date must be older">ERREUR: La date de fin doit être postérieure</string>
<string id="ERROR: Old password incorrect !!">ERREUR: Ancien mot de passe incorrect !!</string>
<string id="ERROR: Passwords not match !!">ERREUR: les mots de passe ne sont pas identiques !!</string>
<string id="ERROR: This FAQ already exists">ERREUR: Cette FAQ existe déjà</string>
<string id="ERROR: This category already exists">ERREUR: Cette catégorie existe déjà</string>
<string id="ERROR: This contact already exists">ERREUR: Ce contact existe déjà</string>
<string id="ERROR: This directory already exists">ERREUR: Cet annuaire existe déjà</string>
<string id="ERROR: This domain already exists">ERREUR: Ce domaine existe déjà</string>
<string id="ERROR: This email account already exists !!">ERREUR: Cette adresse e-mail existe déjà !!</string>
<string id="ERROR: This forum already exists">ERREUR: Ce forum existe déjà</string>
<string id="ERROR: This section already exists">ERREUR: Cette section existe déjà</string>
<string id="ERROR: This site already exists">ERREUR: Ce existe déja</string>
<string id="ERROR: This topic already exists">ERREUR: Ce thème d'articles existe déjà</string>
<string id="ERROR: This topic category doesn't exist">ERREUR: cette catégorie de thèmes d'articles n'existe pas</string>
<string id="ERROR: You must check at least one vacation type">ERREUR: Vous devez cocher au moins un type de congé</string>
<string id="ERROR: You must choose a valid category !!">ERREUR: Vous devez choisir une catégorie valide !!</string>
<string id="ERROR: You must choose a valid forum">ERREUR: Vous devez choisir un forum existant</string>
<string id="ERROR: You must choose a valid group !!">ERREUR: Vous devez choisir un nom de groupe correct !!</string>
<string id="ERROR: You must choose a valid item !!">ERREUR: Vous devez choisir un item valide !!</string>
<string id="ERROR: You must choose a valid notes">ERREUR: Vous devez choisir une note</string>
<string id="ERROR: You must choose a valid question !!">ERREUR: Vous devez choisir une question valide !!</string>
<string id="ERROR: You must choose a valid resource !!">ERREUR: Vous devez choisir une ressource existante !!</string>
<string id="ERROR: You must choose a valid section !!">ERREUR: Vous devez choisir une section valide !!</string>
<string id="ERROR: You must choose a valid topic category !!">ERREUR: Vous devez choisir une catégorie de thèmes d'articles valide !!</string>
<string id="ERROR: You must choose a valid user !!">ERREUR: Vous devez choisir un utilisateur valide !!</string>
<string id="ERROR: You must complete all required fields !!">ERREUR: Vous devez renseigner tous les champs obligatoires !!</string>
<string id="ERROR: You must provide a FAQ !!">ERREUR: Vous devez donnez une FAQ !!</string>
<string id="ERROR: You must provide a FAQ name !!">ERREUR: Vous devez donner un intitulé à la FAQ !!</string>
<string id="ERROR: You must provide a category !!">ERREUR: Vous devez donner une catégorie valide !!</string>
<string id="ERROR: You must provide a content for your message">ERREUR: Vous devez saisir un contenu dans votre message</string>
<string id="ERROR: You must provide a file name">ERREUR: Vous devez fournir un nom de fichier</string>
<string id="ERROR: You must provide a first name">ERREUR: Vous devez donner un nom</string>
<string id="ERROR: You must provide a head for your article">ERREUR: L'introduction de l'article ne doit pas être vide</string>
<string id="ERROR: You must provide a host address !!">ERREUR: Vous devez indiquer l'addresse d'un serveur !!</string>
<string id="ERROR: You must provide a moderator">ERREUR: Vous devez fournir le nom d'un modérateur</string>
<string id="ERROR: You must provide a name !!">ERREUR: Vous devez indiquer un nom !!</string>
<string id="ERROR: You must provide a name">ERREUR: Vous devez fournir un nom</string>
<string id="ERROR: You must provide a subject for your message">ERREUR: Vous devez fournir un sujet pour votre message</string>
<string id="ERROR: You must provide a title !!">ERREUR: Vous devez spécifier un titre !!</string>
<string id="ERROR: You must provide a title">ERREUR: Vous devez fournir un titre</string>
<string id="ERROR: You must provide a valid email address">ERREUR: Vous devez donner une adresse e-mail valide</string>
<string id="ERROR: You must provide account field !!">ERREUR: Vous devez spécifier un compte !!</string>
<string id="ERROR: You must provide at least one approver !!">ERREUR: vous devez indiquez au moins un approbateur !!</string>
<string id="ERROR: You must provide question and response !!">ERREUR: Vous devez donner une question et une réponse !!</string>
<string id="ERROR: You must provide server address !!">ERREUR: Vous devez donner l'addresse d'un serveur !!</string>
<string id="ERROR: You must provide signature !!">ERREUR: Vous devez spécifier une signature !!</string>
<string id="ERROR: You must provide topic manager !!">ERREUR: Vous devez indiquer un gestionnaire pour le thème d'articles !!</string>
<string id="ERROR: Your email is not valid !!">ERREUR: Votre adresse de messagerie n'est pas correct !!</string>
<string id="Edit request vacation">Modifier une demande de congé</string>
<string id="Edit">Editer</string>
<string id="Email a new password">Envoyer un nouveau mot de passe par e-mail</string>
<string id="Email site">Adresse e-mail du site</string>
<string id="Email">Email</string>
<string id="Empty">Vider</string>
<string id="Enabled">Actif</string>
<string id="End date must be older">La date de fin doit être postérieure</string>
<string id="End date">Date de fin</string>
<string id="End">Fin</string>
<string id="Entry date ( dd-mm-yyyy )">Date d'écriture ( jj-mm-aaaa )</string>
<string id="Entry date">Date d'écriture</string>
<string id="Error occured when sending email !!">Une erreur est survenue à l'émission du message !!</string>
<string id="Events categories">Catégories d'évènements</string>
<string id="Everybody">Tout le monde</string>
<string id="Everyday">Chaque jour</string>
<string id="Export requests vacations">Exporter les demandes de congés</string>
<string id="Export">Exporter</string>
<string id="FAQ Name">Intitulé de la FAQ</string>
<string id="FAQ">FAQ</string>
<string id="Faq">Faq</string>
<string id="Faqs">Faqs</string>
<string id="February">Février</string>
<string id="Fields to display">Champs à afficher</string>
<string id="Fields">Champs</string>
<string id="File does'nt exist">Le fichier n'existe pas</string>
<string id="File has been updated">Le fichier a été mis à jour</string>
<string id="File manager">Gest. de fichiers</string>
<string id="File">Fichier</string>
<string id="Filename">Nom du fichier</string>
<string id="Files">Fichiers</string>
<string id="Filter language and country">Filtre sur le langage et le pays</string>
<string id="Filter language">Filtre sur le langage</string>
<string id="Filter on">Filtrer sur</string>
<string id="Filter translated">Filtre traduit</string>
<string id="Find">Trouver</string>
<string id="First day of week">Premier jour de la semaine</string>
<string id="Firstname Lastname">Prénom Nom</string>
<string id="Firstname and Lastname already exists !!">Ce couple Nom/Prénom existe déjà !!</string>
<string id="Firstname">Prénom</string>
<string id="Folder">Répertoire</string>
<string id="Folders">Répertoires</string>
<string id="Follow order">Respecter l'ordre</string>
<string id="Format">Format</string>
<string id="Forums order">Ordre des forums</string>
<string id="Forums">Forums</string>
<string id="Forward">Transférer</string>
<string id="Friday">Vendredi</string>
<string id="From">de</string>
<string id="Full Name">Nom et Prénom</string>
<string id="Fullname">Nom complet</string>
<string id="Global domains list">Liste des domaines</string>
<string id="Global space">Espace global</string>
<string id="Go to Today">Aujourd'hui</string>
<string id="Go to Top">Haut</string>
<string id="Group domains list">Liste des domaines</string>
<string id="Group name">Nom de Groupe</string>
<string id="Group with the same name already exists!">Un groupe avec le même nom existe déjà!</string>
<string id="Group">Groupe</string>
<string id="Group's Domains">Domaines du groupe</string>
<string id="Group's members">Liste des membres du groupe</string>
<string id="Groups List">Liste de groupes</string>
<string id="Groups Names">Liste des groupes</string>
<string id="Groups calendars">Groupes</string>
<string id="Groups list">Liste des groupes</string>
<string id="Groups">Groupes</string>
<string id="Handling duplicates">Comment traiter les doublons</string>
<string id="Head">Introduction</string>
<string id="Hits">Hits</string>
<string id="Home Address">Adresse perso.</string>
<string id="Home Tel">Tél. perso.</string>
<string id="Home folder">Répertoire racine</string>
<string id="Home pages">Les pages d'accueil</string>
<string id="Home">Accueil</string>
<string id="Host">Serveur</string>
<string id="Html">Html</string>
<string id="If you choose to update all occurrences, dates are not be updated !">Si vous choisissez de mettre à jour toute la série, les dates ne sont pas prises en compte !</string>
<string id="Image size must not exceed">La taille de l'image ne doit pas excéder</string>
<string id="Images">Images</string>
<string id="Import file to">Importer un  fichier dans</string>
<string id="Import">Importer</string>
<string id="In the same topic">Dans le même thème d'articles</string>
<string id="Inbox">Boîte de réception</string>
<string id="Incoming mail server port">Port pour le serveur 'entrant'</string>
<string id="Incoming mail server">Serveur de messagerie 'entrant' (Pop/Imap)</string>
<string id="Incorrect nickname">Identifiant incorrect</string>
<string id="Incorrect total number of days">Nombre de jours total est incorrect</string>
<string id="Index of questions">Index des questions</string>
<string id="Information">Information</string>
<string id="Introduction Tag">Balise d'introduction</string>
<string id="Invalid begin date">Date de début invalide</string>
<string id="Invalid end date">Date de fin invalide</string>
<string id="Invalid entry!  Only numbers are accepted and . !">Saisie invalide!  Seulement les chiffres et le point sont acceptés!</string>
<string id="Invalid entry!  Only numbers are accepted or . !">Saisie invalide!  Seulement les chiffres et le point sont acceptés !</string>
<string id="Invalid entry">Saisie invalid</string>
<string id="Invalid image extension">Extension du fichier invalide</string>
<string id="Invalid mail account !!">Compte de messagerie invalide</string>
<string id="January">Janvier</string>
<string id="July">Juillet</string>
<string id="June">Juin</string>
<string id="Kb">Ko</string>
<string id="Keywords">Mots clés</string>
<string id="Lang">Langue</string>
<string id="Language filter">Filtre de la langue</string>
<string id="Last Post">Dernière contribution</string>
<string id="Last articles ( Since seven days before your last visit )">Derniers articles ( Depuis sept jours avant votre dernière visite )</string>
<string id="Last comments ( Since seven days before your last visit )">Derniers commentaires ( Depuis sept jours avant votre dernière visite )</string>
<string id="Last files ( Since seven days before your last visit )">Derniers fichiers ( Depuis sept jours avant votre dernière visite )</string>
<string id="Last posts ( Since seven days before your last visit )">Dernières contributions ( Depuis sept jours avant votre dernière visite )</string>
<string id="Lastname Firstname">Nom Prénom</string>
<string id="Lastname">Nom</string>
<string id="Ldap Directories list">Liste des annuaires ( ldap )</string>
<string id="Ldap Directory">Annuaire Ldap</string>
<string id="Left sections">Sections à gauche</string>
<string id="Left">Gauche</string>
<string id="List of all faqs">Liste de toutes les FAQs</string>
<string id="List of all forums">Liste de tous les forums</string>
<string id="List of all topics">Liste des thèmes d'articles</string>
<string id="List of articles">Liste des articles</string>
<string id="List of comments">Liste des commentaires</string>
<string id="List of different forums">Liste des différents forums</string>
<string id="List of different topics categories">Liste des différentes catégories de thèmes d'articles</string>
<string id="List of groups">Liste des groupes</string>
<string id="List of managed topics">Liste des thèmes d'articles que je gère</string>
<string id="List of old articles">Liste des articles archivés</string>
<string id="List of submitted articles">Liste des articles soumis et en attente de validation</string>
<string id="List of vacations administrators">Liste gestionnaires de congés</string>
<string id="List">Liste</string>
<string id="Login">Connexion</string>
<string id="Logout">Déconnexion</string>
<string id="Lost Password">J'ai perdu mon mot de passe</string>
<string id="Mail domain doesn't exist">Ce domaine de messagerie n'existe pas</string>
<string id="Mail function">Fonction mail</string>
<string id="Mail options">Options de la messagerie</string>
<string id="Mail">Messagerie</string>
<string id="Make available to registered users home page">Proposer pour la page d'accueil privée</string>
<string id="Make available to unregistered users home page">Proposer pour la page d'accueil publique</string>
<string id="Managed topics">Thèmes d'articles managés</string>
<string id="Management">Gestion</string>
<string id="Manager">Gestionnaire</string>
<string id="March">Mars</string>
<string id="Max days authorized">Nombre de jours max. autorisés</string>
<string id="Max days number">Nombre de jours max.</string>
<string id="Max image size ( Kb )">Taille maximale d'une image ( Ko )</string>
<string id="Max">Max</string>
<string id="May">Mai</string>
<string id="Members">Membres</string>
<string id="Message">Message</string>
<string id="Messages Per Page">Nb de messages par page</string>
<string id="Minutes">Minutes</string>
<string id="Mobile Tel">Tél. portable</string>
<string id="Moderate">Modérer</string>
<string id="Moderation">Modération</string>
<string id="Moderator Email">Modérateur</string>
<string id="Moderator">Modérateur</string>
<string id="Modifiable">Modifiable</string>
<string id="Modified by">Modifié par</string>
<string id="Modified">Modifié</string>
<string id="Modify Account">Modifier le compte</string>
<string id="Modify Category">Modifier la catégorie</string>
<string id="Modify FAQ">Modifier la FAQ</string>
<string id="Modify Group">Modifier le groupe</string>
<string id="Modify Resource">Modifier la ressource</string>
<string id="Modify Signature">Modifier une signature</string>
<string id="Modify Status">Modifier un status</string>
<string id="Modify a forum">Modifier un forum</string>
<string id="Modify a note">Modifier une note</string>
<string id="Modify a topic">Modifier un thème d'article</string>
<string id="Modify a user">Modifier un utilisateur</string>
<string id="Modify account">Modifier un compte</string>
<string id="Modify contact">Modifier le contact</string>
<string id="Modify directory">Modifier l'annuaire</string>
<string id="Modify folder">Modifier le répertoire</string>
<string id="Modify mail domain">Modifier le domaine</string>
<string id="Modify question">Modifier la question</string>
<string id="Modify status">Modifier un statut</string>
<string id="Modify topic category">Modifier une catégorie de thèmes d'articles</string>
<string id="Modify user">Modifier un utilisateur</string>
<string id="Modify vacation right">Modifier un droit de congé</string>
<string id="Modify vacation type">Modifier un type de congé</string>
<string id="Modify vacation type's collection">Modifier un régime de congé</string>
<string id="Modify vacation">Modifier le type de congés</string>
<string id="Modify">Modifier</string>
<string id="Monday">Lundi</string>
<string id="Month">Mois</string>
<string id="Morning">Matin</string>
<string id="Move Down">Vers le bas</string>
<string id="Move Up">Vers le haut</string>
<string id="Move selected articles from archive">Déplacer les articles sélectioonnés des archives</string>
<string id="Move to folder">Déplacer vers le répertoire</string>
<string id="Multilignes">Multilignes</string>
<string id="Name">Nom</string>
<string id="New Password">Nouveau mot de passe</string>
<string id="New article for home page">Nouveau article pour la page d'accueil</string>
<string id="New articles">Nouveaux articles</string>
<string id="New calendar event">Nouvel évènement</string>
<string id="New comments">Nouveaux commentaires</string>
<string id="New file">Nouveau fichier</string>
<string id="New files">Nouveaux fichiers</string>
<string id="New post">Nouvelle contribution</string>
<string id="New posts">Nouvelles contributions</string>
<string id="New reply">Nouvelle contribution</string>
<string id="New thread">Nouveau sujet</string>
<string id="New waiting article">Nouvel article en attente</string>
<string id="New waiting comment">Nouveau commentaire en attente</string>
<string id="New waiting file">Nouveau fichier en attente</string>
<string id="New">Nouveau</string>
<string id="Next day">Jour suivant</string>
<string id="Next time">Suivant</string>
<string id="Next">Suivant</string>
<string id="Nickname">Identifiant</string>
<string id="No filter">Pas de filtre</string>
<string id="No">Non</string>
<string id="None">Aucun</string>
<string id="Note: Articles are moderate and consequently your article will not be visible immediately">Attention: Les articles sont modérées et par conséquent votre article ne sera pas visible immédiatement</string>
<string id="Note: Posts are moderate and consequently your post will not be visible immediately">Attention: Les contributions sont modérées et par conséquent votre contribution ne sera pas visible immédiatement</string>
<string id="Note: for this topic, comments are moderate">Attention: Pour ce thème d'articles, les commentaires sont modérés</string>
<string id="Notes list">Liste des notes</string>
<string id="Notes">Notes</string>
<string id="Nothing Changed">Rien n'a été modifié</string>
<string id="Notification">Notification</string>
<string id="Notify group members by mail">Notifier les membres du groupe par email</string>
<string id="Notify me whenever someone replies ( only valid for registered users )">Me prévenir par e-mail quand quelqu'un contribue ( uniquement pour les utilisateurs enregistrés )</string>
<string id="Notify members group">Notifier les membres du groupe</string>
<string id="Notify moderator">Notifier le modérateur</string>
<string id="Notify user">Notifier l'utilisateur</string>
<string id="Notify users">Notifier les utilisateurs</string>
<string id="Notify">Notifier</string>
<string id="November">Novembre</string>
<string id="Number of topics">Nombre de thèmes d'articles</string>
<string id="October">Octobre</string>
<string id="Old Password">Ancien mot de passe</string>
<string id="On create new event, check">Lors de la création d'un nouvel événement, cocher</string>
<string id="On site">Sur le site</string>
<string id="Only valid if registration is actif">Seulement valide si l'inscription est active</string>
<string id="Open thread">Ouvrir le sujet</string>
<string id="Opened right">Droit ouvert</string>
<string id="Opened rights">Droits ouverts</string>
<string id="Opened threads">Sujets ouverts</string>
<string id="Options">Options</string>
<string id="Or users having ">Ou les utilisateurs ayant pour régime</string>
<string id="Or">Ou</string>
<string id="Order forums">Ordonner les forums</string>
<string id="Order">Ordre</string>
<string id="Original Message">Message original</string>
<string id="Other">Autre</string>
<string id="Outgoing mail server port">Port pour le serveur 'sortant'</string>
<string id="Outgoing mail server">Serveur de messagerie 'sortant' (SMTP)</string>
<string id="Ovidentia Administrator">Administrateur d'Ovidentia</string>
<string id="Ovidentia info">Ovidentia informations</string>
<string id="Ovidentia version">Version d'Ovidentia</string>
<string id="PHP script">Script PHP</string>
<string id="Password Changed">Le mot de passe a été modifié</string>
<string id="Password Reset">Re-initialiser le mot de passe</string>
<string id="Password incorrect">Mot de passe incorrect</string>
<string id="Password must be at least 6 characters !!">Le mot de passe doit comporter au moins 6 caractères !!</string>
<string id="Password">Mot de passe</string>
<string id="Passwords not match !!">Mot de passe non trouvé !!</string>
<string id="Paste">Coller</string>
<string id="Path">Chemin</string>
<string id="Period">Période</string>
<string id="Personal disk space">Espace disque personnel</string>
<string id="Personnal Folder">Dossier personnel</string>
<string id="Personnel">Personnel</string>
<string id="Php version">Version du moteur PHP</string>
<string id="Plain text">Texte</string>
<string id="Planning">Planning</string>
<string id="Please give a valid directory name">Veuillez spécifier un nom de répertoire correct</string>
<string id="Please provide a valid email.">Merci d'indiquer une adresse e-mail correct</string>
<string id="Please select a file to upload">Séléctionnez un fichier à télécharger</string>
<string id="Please select at least one item">SVP, veuillez sélectionner au moins un élément</string>
<string id="Position">Position</string>
<string id="Post">Poster</string>
<string id="Posted by">Chargé par</string>
<string id="Posts">Contributions</string>
<string id="Prefered account">Compte préféré</string>
<string id="Prefered format">Format préféré</string>
<string id="Prefered language">Langage préféré</string>
<string id="Prefered skin">Skin préféré</string>
<string id="Prefered style">Style préféré</string>
<string id="Previous day">Jour précédent</string>
<string id="Previous time">Précédent</string>
<string id="Previous">Précédent</string>
<string id="Primary group">Groupe primaire</string>
<string id="Print Friendly">Impression</string>
<string id="Print">Imprimer</string>
<string id="Private home page articles">Liste des articles de la page d'accueil privée</string>
<string id="Private">Privée</string>
<string id="Public home page articles">Liste des articles de la page d'accueil public</string>
<string id="Public">Publique</string>
<string id="Quantities">Quantités</string>
<string id="Quantity">Quantité</string>
<string id="Question">Question</string>
<string id="Questions and Answers">Questions et Réponses</string>
<string id="Questions">Questions</string>
<string id="Re-type SMTP password">Retapez le mot de passe SMTP</string>
<string id="Read More">Lire la suite</string>
<string id="Read article">Lire l'article</string>
<string id="Read more">Suite</string>
<string id="Read only">Lecture seule</string>
<string id="Reasons of refusal">Raisons du refus</string>
<string id="Recent posts">Contributions récentes</string>
<string id="Refresh">Actualiser</string>
<string id="Refuse">Refuser</string>
<string id="Refused">Refusé</string>
<string id="Register">Je veux m'enregistrer</string>
<string id="Registered Users">Utilisateurs enregistrés</string>
<string id="Registered users home page for site">Page d'accueil privée (utilisateurs enregistrés)</string>
<string id="Registered users home page">Page d'accueil privée</string>
<string id="Registered users">Utilisateurs enregistrés</string>
<string id="Registration Confirmation">Confirmation d'inscription</string>
<string id="Remaining">Restant</string>
<string id="Remarks">Remarques</string>
<string id="Rename">Renommer</string>
<string id="Repeat">Répéter</string>
<string id="Replace duplicates with items imported">Remplacer les doublons par celui de l'importation</string>
<string id="Replies">Contributions</string>
<string id="Reply to all">Répondre à tous</string>
<string id="Reply">Répondre</string>
<string id="Request vacation">Demande de congé</string>
<string id="Request vacations waiting to be validate">Demandes de congés en attente de validation</string>
<string id="Request">Demander</string>
<string id="Requests vacations list">Liste des demandes de congés</string>
<string id="Requests">Demandes</string>
<string id="Required">Obligatoire</string>
<string id="Reset">Réinitialiser</string>
<string id="Resources calendars">Ressources</string>
<string id="Resources">Ressources</string>
<string id="Response">Réponse</string>
<string id="Restore">Restaurer</string>
<string id="Return to Questions">Revenir à la liste des questions</string>
<string id="Retype New Password">Retapez le nouveau mot de passe</string>
<string id="Retype Paasword">Retapez le mot de passe</string>
<string id="Retype default password">Retapez le mot de passe</string>
<string id="Right closed">Droit fermé</string>
<string id="Right opened">Droit ouvert</string>
<string id="Right sections">Sections à droite</string>
<string id="Right">Droite</string>
<string id="Rights">Droits</string>
<string id="Rows">Lignes</string>
<string id="SMTP password">Mot de passe SMTP</string>
<string id="SMTP username">Login SMTP</string>
<string id="Saturday">Samedi</string>
<string id="Schemas list">Liste des schémas d'approbation</string>
<string id="Schemas">Les schémas</string>
<string id="Search result empty">Résultat de la recherche vide</string>
<string id="Search">Rechercher</string>
<string id="Sections list">Liste des sections</string>
<string id="Sections order">Ordre des sections</string>
<string id="Sections">Sections</string>
<string id="Select destinataire">Sélectionner un destinataire</string>
<string id="Select signature">Sélectionner une signature</string>
<string id="Send an email to author">Envoyer un message à l'auteur</string>
<string id="Send email confirmation">Envoyer un email de confirmation</string>
<string id="Send password with email">Envoyer le mot de passe avec l'email</string>
<string id="Send">Envoyer</string>
<string id="Sending error( Mail sending disabled )">Erreur d'envoi ( L'envoi d'email est désactivé )</string>
<string id="Separator">Separateur</string>
<string id="September">Septembre</string>
<string id="Server port">Port du serveur</string>
<string id="Shared">Partagé</string>
<string id="Show disk space usage">Montrer l'espace disque utilisé</string>
<string id="Signature">Signature</string>
<string id="Signatures">Signatures</string>
<string id="Since your last connection:">Depuis votre dernière connexion:</string>
<string id="Site directory">Annuaire</string>
<string id="Site name">Nom de site</string>
<string id="Sites list">Liste des sites</string>
<string id="Sites">Sites</string>
<string id="Size">Taille</string>
<string id="Skin">Skin</string>
<string id="Smtp server">Serveur SMTP</string>
<string id="Sorry - You haven't Confirmed Your Account Yet">Désolé, vous n'avez pas encore confirmé votre inscription</string>
<string id="Sorry, You cannot change your password. Please contact administrator">Désolé, vous ne pouvez pas modifier votre mot de passe. Contactez l'administrateur</string>
<string id="Sorry, you cannot delete this user. He is already logged">Désolé, vous ne pouvez pas détruire cet utilisateur car il est connecté</string>
<string id="Sorry, your account is disabled. Please contact your adminsitrator">Désolé, votre compte est inactif. Veuillez contacter l'administrateur</string>
<string id="Sort ascending">Tri croissant</string>
<string id="Sort descending">Tri décroissant</string>
<string id="Starter">Initiateur</string>
<string id="Status">Statut</string>
<string id="Subject">Sujet</string>
<string id="Submit an article">Soumettre un article</string>
<string id="Submit">Soumettre</string>
<string id="Submiter">Auteur</string>
<string id="Submitted">Soumis</string>
<string id="Summary of information about">Résumé d'informations de</string>
<string id="Summary">Résumé</string>
<string id="Sunday">Dimanche</string>
<string id="Tab">Tabulation</string>
<string id="Thank You For Registering at our site">Merci pour votre inscription sur notre site</string>
<string id="The category doesn't exist">La catégorie n'existe pas</string>
<string id="The file could not be uploaded">Le fichier ne peut être chargé</string>
<string id="The file was greater than the maximum allowed">La taille du fichier est plus grande que la taille autorisée</string>
<string id="The resource doesn't exist">La ressource n'existe pas</string>
<string id="The state doesn't exist">L'état n'existe pas</string>
<string id="There are no submitted article">Il n'y a pas d'article soumis en attente de validation</string>
<string id="There is no forum">Il n'y a pas de forum</string>
<string id="There is no section">Il n'y a pas de section</string>
<string id="There is no site">Il n'y a pas de site</string>
<string id="There is no topic">Il n'y a pas de thème d'articles</string>
<string id="There is no waiting vacation request">Il n'y a pas de demande de congé en attente</string>
<string id="There is not enough free space">Il n'y a pas assez d'espace disque</string>
<string id="This collection already exists">Ce régime existe déjà</string>
<string id="This flow approvers already exists">Ce shéma d'approbation existe déjjà</string>
<string id="This folder already exists">Ce répertoire existe déjà</string>
<string id="This group already exists">Ce groupe existe déjà</string>
<string id="This is a reccuring event.Are you sure you want to delete this event and all occurrences">Ceci est un évènement répétitif. Etes-vous sûr de vouloir supprimer toute la série</string>
<string id="This is recurring event. Do you want to update this occurence or series?">Ceci est un évènement répétitif. Voulez-vous mettre à jour cet évènement ou toute la série?</string>
<string id="This is recurring event. Do you want to update this ocuurence or series?">Ceci est un évènement répétitif. Voulez-vous mettre à jour cet évènement ou toute la série?</string>
<string id="This nickname already exists !!">Cet identifiant existe déjà</string>
<string id="This occurence">Cet évènement</string>
<string id="This resource already exists">Cette ressource existe déjà</string>
<string id="This section is for Administration">Cette section est pour l'administration du site</string>
<string id="This topic category already exists">Cette catégorie de thèmes d'articles existe déjà</string>
<string id="This user already exist in personnel list">Cet utilisateur existe déjà dans la liste du personnel</string>
<string id="This user does'nt exist in personnel list">Cet utilisateur ne fait pas partie du personnel</string>
<string id="This vacation collection is used and can't be deleted">Ce régime est utilisé et ne peut être supprimé</string>
<string id="This vacation type already exists">Ce type de congé existe déjà</string>
<string id="This vacation type is used and can't be deleted">Ce type de congé ne peut être supprimé, il est déjà utilisé</string>
<string id="Those fields must be filled">Ces champs doivent être remplis</string>
<string id="Thread">Sujet</string>
<string id="Threads Per Page">Sujets par page</string>
<string id="Threads">Sujets</string>
<string id="Thursday">Jeudi</string>
<string id="Time scale">Echelle du temps</string>
<string id="To confirm your registration">Pour confirmer votre enregistrement</string>
<string id="To connect on our site">Pour se connecter sur notre site</string>
<string id="To delete topic category, you must delete topics before">Pour supprimer une catégorie de thèmes d'articles, vous devez supprimer d'abord les thèmes d'articles</string>
<string id="To let user log on your site, you must confirm his registration">Pour permettre à l'utilisateur de se connecter sur votre site, vous devez confirmer son inscription</string>
<string id="To">à</string>
<string id="Today, there are no article">Aujourd'hui, il n'y a pas d'articles</string>
<string id="Today, there is no comment on this article">Aujourd'hui, il n'y a aucun commentaire pour cet article</string>
<string id="Topic category">Catégorie de thèmes d'articles</string>
<string id="Topic manager">Gestionnaire du thème d'articles</string>
<string id="Topic">thème d'articles</string>
<string id="Topics categories">Catégories de thèmes d'articles</string>
<string id="Topics with asterisk have waiting articles or comments ">Les thèmes marqués d'un "*" ont des articles ou des commentaires en attente</string>
<string id="Topics">Thèmes d'articles</string>
<string id="Total access">Accès total</string>
<string id="Total days does'nt fit between dates">Le nombre de jours total est plus grand que l'intervalle de temps</string>
<string id="Total">Total</string>
<string id="Trash">Corbeille</string>
<string id="Tuesday">Mardi</string>
<string id="Type">Type</string>
<string id="Types">Types</string>
<string id="Uncheck all mails">Dé-sélectionner tous les messages</string>
<string id="Uncheck all">Tout dé-sélectionner</string>
<string id="Undo">Annuler</string>
<string id="Unknown user">Utilisateur inconnu</string>
<string id="Unregistered Users">Utilisateurs non enregistrés</string>
<string id="Unregistered users home page for site">Page d'accueil publique (utilisateurs non enregistrés)</string>
<string id="Unregistered users home page">Page d'accueil publique</string>
<string id="Unregistered users">Utilisateurs non enregistrés</string>
<string id="Until date">Jusqu'à une date</string>
<string id="Until">Until</string>
<string id="Upcoming Events ( in the seven next days )">Evènements à venir ( dans les sept jours prochains )</string>
<string id="Update Contact">Modifier le contact</string>
<string id="Update Event">Modifier l'événement</string>
<string id="Update FAQ">Mettre à jour la FAQ</string>
<string id="Update Forum">Modifier le forum</string>
<string id="Update Groups">Mettre à jour</string>
<string id="Update Info">Modifier les infos</string>
<string id="Update Language">Mise à jour du langage</string>
<string id="Update Note">Mettre à jour la note</string>
<string id="Update Password">Modifier le mot de passe</string>
<string id="Update Question">Mettre à jour la question</string>
<string id="Update Skin">Mise à jour du skin</string>
<string id="Update Topic">Mettre à jour un thème d'article</string>
<string id="Update access">Modifier l'accès</string>
<string id="Update failed">La mise à jour a échoué</string>
<string id="Update reply">Modifier la réponse</string>
<string id="Update">Mettre à jour</string>
<string id="Upload file to">Charger un fichier dans</string>
<string id="Upload">Charger</string>
<string id="Use AM PM">Utiliser AM PM</string>
<string id="Use bacground color for events">Utiliser les couleurs d'événements</string>
<string id="Use email">Fonction messagerie</string>
<string id="Used">Utilisé</string>
<string id="User Account Updated - You can now log to our site">Votre inscription est confirmée, vous pouvez maintenant vous connecter sur notre site</string>
<string id="User DN">User DN</string>
<string id="User Name">Nom d'utilisateur</string>
<string id="User Not Found">Utilisateur inconnu</string>
<string id="User does'nt exist">L'utilisateur n'existe pas</string>
<string id="User email">E-Mail de l'utilisateur</string>
<string id="User is already in the list!">Cette utilisteur est déjà dans la liste!</string>
<string id="User not found or bad password">Utilisateur inconnu ou mot de passe erroné</string>
<string id="User not found or password incorrect">Utilisateur inconnu ou mot de passe erroné</string>
<string id="User">Utilisateur</string>
<string id="User's Domains">Domaines privés</string>
<string id="User's section">Utilisateur</string>
<string id="Users calendars">Utilisateurs</string>
<string id="Users does'nt exist">Les utilisateurs n'existent pas</string>
<string id="Users list">Liste des utilisateurs</string>
<string id="Users">Utilisateurs</string>
<string id="Vac. closed">Fermé</string>
<string id="Vac. opened">Ouvert</string>
<string id="Vacation entry has been updated">Demande de congé mise à jour</string>
<string id="Vacation has been accepted">Demande de congé acceptée</string>
<string id="Vacation has been refused">Demande de congé refusée</string>
<string id="Vacation is waiting to be validated">Un demande de congé est en attente de validation</string>
<string id="Vacation request is waiting to be validated">Une demande de congés est en attente de validation</string>
<string id="Vacation request">Demande de congés</string>
<string id="Vacation requests list">Liste des demandes de congés</string>
<string id="Vacation rights of:">Droits de congé de:</string>
<string id="Vacation type">Type de congés</string>
<string id="Vacation">Congés</string>
<string id="Vacations rights">Droits de congés</string>
<string id="Vacations type's collections">Liste des régimes de congés</string>
<string id="Vacations types">Types de congés</string>
<string id="Vacations">Congés</string>
<string id="Validation">Validation</string>
<string id="Version">Version</string>
<string id="Versions">Versions</string>
<string id="View categories">Voir les categories</string>
<string id="View this account">Consulter cette boîte aux lettres</string>
<string id="View those calendars">Afficher ces calendriers</string>
<string id="View thread as flat list">Visualiser le sujet en mode plat</string>
<string id="View thread as hierarchical list">Visualiser le sujet en mode hiérarchique</string>
<string id="View">Voir</string>
<string id="Views">Consultations</string>
<string id="WARNING: This operation will delete all entries">ATTENTION: Cette opération supprime toutes les entrées</string>
<string id="WARNING: This operation will delete all occurrences permanently">ATTENTION: cette opération supprime toute la série définitivement</string>
<string id="WARNING: This operation will delete articles and their comments">ATTENTION: Cette opération va supprimer les articles ainsi que les commentaires associés</string>
<string id="WARNING: This operation will delete contacts and their references">ATTENTION:  Cette opération supprimera les contacts ainsi que leurs références</string>
<string id="WARNING: This operation will delete directory and all references">ATTENTION: Cette opération supprime l'annuaire et ses références</string>
<string id="WARNING: This operation will delete event permanently">ATTENTION: Cette opération détruira définitivement l'événement</string>
<string id="WARNING: This operation will delete members and their references">ATTENTION: Cette opération va supprimer les utilisateurs ainsi que leurs références</string>
<string id="WARNING: This operation will delete question and its response">ATTENTION: Cette opération va détruire la question et la réponse associée</string>
<string id="WARNING: This operation will delete schema and all references">ATTENTION: Cette opération supprime toutes les références à ce schéma d'approbation</string>
<string id="WARNING: This operation will delete the FAQ with all questions and responses">ATTENTION: Cette action supprime la FAQ avec les questions et les réponses</string>
<string id="WARNING: This operation will delete the account and all references">ATTENTION: Cette opération supprimera le compte ainsi que ses références</string>
<string id="WARNING: This operation will delete the article with all its comments">ATTENTION: cette opération supprimera l'article et tous ses commentaires</string>
<string id="WARNING: This operation will delete the category with all references">ATTENTION: Cette opération supprimera la catégorie et tous les éléments qui y font référence</string>
<string id="WARNING: This operation will delete the comment with all its replys">ATTENTION: cette opération supprimera le commentaire et toutes les réponses associées</string>
<string id="WARNING: This operation will delete the domain with all references">ATTENTION: Cette opération supprimera le domaine ainsi que ses références</string>
<string id="WARNING: This operation will delete the folder with all files">ATTENTION: Cete opération supprime le répertoire et tous les fichiers</string>
<string id="WARNING: This operation will delete the forum and all posts">ATTENTION: Cette opération supprimera le forum avec tous ses sujets de discussion</string>
<string id="WARNING: This operation will delete the group with all references">ATTENTION: Cette opération supprimera le groupe et tous les éléments qui y font référence</string>
<string id="WARNING: This operation will delete the resource with all references">ATTENTION: Cette opération va supprimer la ressource et toutes ses références</string>
<string id="WARNING: This operation will delete the section and all references">ATTENTION: Cette opération supprimera la section et tous les éléments qui y font référence</string>
<string id="WARNING: This operation will delete the site and all references">ATTENTION: Cette opération va supprimer ce site et toutes ses références</string>
<string id="WARNING: This operation will delete the status and all references">ATTENTION: Cette opération va supprimer cet état et toutes ses références</string>
<string id="WARNING: This operation will delete the thread and all references">ATTENTION: Cette opération supprimera le sujet et tous les éléments qui s'y rattachent</string>
<string id="WARNING: This operation will delete the topic category with all references">ATTENTION: Cette opération supprimera la catégorie de thèmes d'articles et tous les éléments qui y font référence</string>
<string id="WARNING: This operation will delete the topic, articles and comments">ATTENTION: Cette opération supprimera le thème d'articles ainsi que tous les articles et commentaires associés</string>
<string id="WARNING: This operation will delete the user and all references">ATTENTION: Cette opération supprimera l'utilisateur et tous les éléments qui y font référence</string>
<string id="WARNING: This operation will delete the vacation and all references">ATTENTION: Cette opération va supprimer ce type de congés et toutes ses références</string>
<string id="WARNING: This operation will delete vacation request">ATTENTION: Cette opération supprime la demande de congé</string>
<string id="WARNING: This operation will delete vacations requests">ATTENTION: cette opération supprime les demandes de congés</string>
<string id="WARNING: This operation will remove users and their references">ATTENTION: cette opération supprime les utilisateurs et leurs références</string>
<string id="Waiting Comment">Commentaire en attente</string>
<string id="Waiting articles">Articles en attente</string>
<string id="Waiting comments">Commentaires en attente</string>
<string id="Waiting mails">Messages</string>
<string id="Waiting posts">Contributions en attente</string>
<string id="Waiting to be valiadte by">En attente de validation par</string>
<string id="Waiting vacation request">Demande de congé en attente</string>
<string id="Waiting">En attente</string>
<string id="We will send you an email for confirmation before you can use our services">Nous allons vous adresser un e-mail pour confirmation pour que vous puissiez utiliser nos services</string>
<string id="Web site">Site WEB</string>
<string id="Wednesday">Mercredi</string>
<string id="Week default view">Vue par défaut de la semaine</string>
<string id="Week">Semaine</string>
<string id="Whole day">Journée entière</string>
<string id="Write">Mis à jour</string>
<string id="Yes">Oui</string>
<string id="You are logged on as">Vous êtes connecté sous le nom</string>
<string id="You are not yet logged in">Vous n'êtes pas connecté</string>
<string id="You don't have access to this contact">Vous n'avez pas l'accès à ce contact</string>
<string id="You don't have permission to create directory">Vous n'avez pas la permission de créer un répertoire</string>
<string id="You don't have permission to remove directory">Vous n'avez pas la permission de supprimer le répertoire</string>
<string id="You don't have permission to rename directory">Vous n'avez pas la permission de renommer le répertoire</string>
<string id="You have been registered on our site">Vous avez été enregistré sur notre sîte</string>
<string id="You language file has been updated">Votre fichier langue a été mis à jour</string>
<string id="You must choose a valid category !!">Vous devez choisir une catégorie existante</string>
<string id="You must choose a valid domain !!">Vous devez choisir un domaine de messagerie existant !!</string>
<string id="You must choose a valid status">Vous devez choisir un état valide</string>
<string id="You must choose a valid vacation">Vous devez choisir un type de congés existant</string>
<string id="You must complete all fields !!">Vous devez renseigner tous les champs !!</string>
<string id="You must complete firstname and lastname fields !!">Vous devez spécifier le nom et le prénom !!</string>
<string id="You must complete required fields">Vous devez compléter les champs obligatoires</string>
<string id="You must fill message field !!">Vous devez rédiger un message !!</string>
<string id="You must fill subject field !!">Vous devez renseigner l'objet !!</string>
<string id="You must fill to field !!">Vous devez préciser au moins un destinataire !!</string>
<string id="You must provide a correct date">Vous devez donner une date valide</string>
<string id="You must provide a name !!">Vous devez spécifier un nom !!</string>
<string id="You must provide a name">Vous devez spécifier un nom</string>
<string id="You must provide a title">Vous devez spécifier un titre</string>
<string id="You must provide an incoming mail server">Vous devez spécifier un serveur de messagerie entrant</string>
<string id="You must provide an outgoing mail server">Vous devez spécifier un serveur de messagerie sortant</string>
<string id="You must select at least one calendar type">Vous devez sélectionner au moins un type de calendrier</string>
<string id="You must select at least one group">Vous devez sélectionner au moins un groupe</string>
<string id="You must specify a correct number days">Vous devez indiquez un nombre de jours correct</string>
<string id="You must specify a user or collection">Vous devez spécifier un utilisateur ou un régime</string>
<string id="You must specify a user or group">Vous devez spécifier un utilisateur ou un groupe</string>
<string id="You must specify a vacation collection">Vous devez spécifier un régime</string>
<string id="You must specify a vacation description">Vous devez spécifiez une description</string>
<string id="You must specify approbation schema">Vous devez spécifier un schéma d'approbation</string>
<string id="You site has been updated">Votre site a été mis à jour</string>
<string id="You site is already up to date">Votre site est déjà à jour</string>
<string id="You will receive an email which let you confirm your registration.">Vous allez recevoir un e-mail qui vous permettra de confirmer votre inscription.</string>
<string id="Your Name">Votre Nom</string>
<string id="Your article has been accepted">Votre article a été accepté</string>
<string id="Your article has been refused">Votre article a été refusé</string>
<string id="Your contact has been added">Votre contact a été ajouté</string>
<string id="Your contact has been deleted">Votre contact a été supprimé</string>
<string id="Your contact has been updated">Votre contact a été mis à jour</string>
<string id="Your contacts list has been updated">Votre liste de contacts a été mise à jour</string>
<string id="Your email is not valid !!">Votre adresse e-mail n'est pas correct !!</string>
<string id="Your event has been updated">Votre évènement a été mis à jour</string>
<string id="Your file list has been updated">Votre fichier a été mis à jour</string>
<string id="Your message has been sent">Votre message a été envoyé</string>
<string id="Your new password has been emailed to you.">Votre nouveau mot de passe vous a été envoyé par e-mail</string>
<string id="Your nickname">Votre identifiant</string>
<string id="Your password has been reset to">Votre mot de passe a été re-initialisé à</string>
<string id="Your registration has been confirmed.">Votre inscription a été confirmé.</string>
<string id="Your request has been updated">Votre demande a été exécutée</string>
<string id="Your site recorded a new registration on behalf of">Votre site a enregistré une nouvelle inscription de</string>
<string id="Your vacation request has been accepted">Votre demande de congé a été accepté</string>
<string id="Your vacation request has been refused">Votre demande de congé a été refusé</string>
<string id="by">par</string>
<string id="bytes">octets</string>
<string id="category">catégorie</string>
<string id="comments - ERROR: You must provide a comment">ERREUR: Vous devez donnez un commentaire</string>
<string id="comments - ERROR: You must provide a title">ERREUR: Vous devez donnez un titre à votre commentaire</string>
<string id="comments-Comment">Commentaire</string>
<string id="comments-Title">Titre du commentaire</string>
<string id="days">jours</string>
<string id="dd-mm-yyyy">jj-mm-aaaa</string>
<string id="endtime">Heure de fin</string>
<string id="from">de</string>
<string id="go to this url">dirigez votre browser à cette url</string>
<string id="group">groupe</string>
<string id="in">dans</string>
<string id="is visible by">est visible à</string>
<string id="link">Lien</string>
<string id="mail domain">domaine</string>
<string id="none">vide</string>
<string id="resource">ressource</string>
<string id="simply follow this">cliquez simplement sur ce</string>
<string id="starttime">Heure de début</string>
<string id="topics categories list">Liste des catégories de thèmes d'articles</string>
<string id="until">jusqu'à</string>
<string id="Title">Titre</string>
<string id="First Name">Prénom</string>
<string id="Middle Name">Deuxième prénom</string>
<string id="Last Name">Nom</string>
<string id="Suffix">Suffixe</string>
<string id="Company">Société</string>
<string id="Department">Service</string>
<string id="Job Title">Titre</string>
<string id="Business Street">Rue (bureau)</string>
<string id="Business Street 2">Rue (bureau) 2</string>
<string id="Business Street 3">Rue (bureau) 3</string>
<string id="Business City">Ville (bureau)</string>
<string id="Business State">Dép/Région (bureau)</string>
<string id="Business Postal Code">Code postal (bureau)</string>
<string id="Business Country">Pays (bureau)</string>
<string id="Home Street">Rue (domicile)</string>
<string id="Home Street 2">Rue (domicile) 2</string>
<string id="Home Street 3">Rue (domicile) 3</string>
<string id="Home City">Ville (domicile)</string>
<string id="Home State">Dép/Région (domicile)</string>
<string id="Home Postal Code">Code postal (domicile)</string>
<string id="Home Country">Pays (domicile)</string>
<string id="Other Street">Rue (autre)</string>
<string id="Other Street 2">Rue (autre) 2</string>
<string id="Other Street 3">Rue (autre) 3</string>
<string id="Other City">Ville (autre)</string>
<string id="Other State">Dép/Région (autre)</string>
<string id="Other Postal Code">Code postal (autre)</string>
<string id="Other Country">Pays (autre)</string>
<string id="Assistant's Phone">Téléphone de l'assistant(e)</string>
<string id="Business Fax">Télécopie (bureau)</string>
<string id="Business Phone">Téléphone (bureau)</string>
<string id="Business Phone 2">Téléphone 2 (bureau)</string>
<string id="Callback">Rappel</string>
<string id="Car Phone">Téléphone (voiture)</string>
<string id="Company Main Phone">Téléphone société</string>
<string id="Home Fax">Télécopie (domicile)</string>
<string id="Home Phone">Téléphone (domicile)</string>
<string id="Home Phone 2">Téléphone 2 (domicile)</string>
<string id="ISDN">RNIS</string>
<string id="Mobile Phone">Tél. mobile</string>
<string id="Other Fax">Télécopie (autre)</string>
<string id="Other Phone">Téléphone (autre)</string>
<string id="Pager">Récepteur de radiomessagerie</string>
<string id="Primary Phone">Téléphone principal</string>
<string id="Radio Phone">Radio téléphone</string>
<string id="TTY/TDD Phone">Téléphone TDD/TTY</string>
<string id="Telex">Télex</string>
<string id="Account">Compte</string>
<string id="Anniversary">Anniversaire de mariage ou fête</string>
<string id="Assistant's Name">Nom de l'assistant(e)</string>
<string id="Billing Information">Informations facturation</string>
<string id="Birthday">Anniversaire</string>
<string id="Children">Enfants</string>
<string id="Directory Server">Serveur d'annuaire</string>
<string id="E-mail Address">Adresse de messagerie</string>
<string id="E-mail Display Name">Nom complet de l'adresse de messagerie</string>
<string id="E-mail 2 Address">Adresse de messagerie 2</string>
<string id="E-mail 2 Display Name">Nom complet de l'adresse de messagerie 2</string>
<string id="E-mail 3 Address">Adresse de messagerie 3</string>
<string id="E-mail 3 Display Name">Nom complet de l'adresse de messagerie 3</string>
<string id="Gender">Sexe</string>
<string id="Government ID Number">Code gouvernement</string>
<string id="Hobby">Passe-temps</string>
<string id="Initials">Initiales</string>
<string id="Internet Free Busy">Disponibilité Internet</string>
<string id="Language">Langue</string>
<string id="Location">Emplacement</string>
<string id="Manager's Name">Responsable</string>
<string id="Mileage">Kilométrage</string>
<string id="Office Location">Bureau</string>
<string id="Organizational ID Number">Numéro d'identification de l'organisation</string>
<string id="PO Box">B.P.</string>
<string id="Priority">Priorité</string>
<string id="Profession">Profession</string>
<string id="Referred By">Recommandé par</string>
<string id="Sensitivity">Critère de diffusion</string>
<string id="Spouse">Conjoint(e)</string>
<string id="User 1">Utilisateur 1</string>
<string id="User 2">Utilisateur 2</string>
<string id="User 3">Utilisateur 3</string>
<string id="User 4">Utilisateur 4</string>
<string id="Web Page">Page Web</string>
<string id="Photo">Photo</string>
<string id="Common Name">Surnom</string>
<string id="Groupes">Groupes</string>
<string id="Retype Password">Retapez le mot de passe</string>
<string id="Edit file">Verrouiller</string>
<string id="Unedit file">Déverrouiller</string>
<string id="Commit file">Charger</string>
<string id="Versioning">Versionnage</string>
<string id="Field">Champ</string>
<string id="Delete fields">Supprimer les champs</string>
<string id="Field name">Libellé du champ</string>
<string id="Default value">Valeur par défaut</string>
<string id="Modfiy">Modifier</string>
<string id="Are you sure you want to delete selected fields">Etes-vous sûr de vouloir supprimer les champs séléctionnés</string>
<string id="WARNING: This operation will delete those fields with their values">ATTENTION: Cette opération supprime ces champs et leurs valeurs</string>
<string id="This field already exists">Ce champ existe déjà</string>
<string id="Modify folder's field">Modifier un champ</string>
<string id="Add folder's field">Ajouter un champ</string>
<string id="Delete folder's fields">Supprimer un champ</string>
<string id="Folder's fields">Champs associés à un répertoire</string>
<string id="This file is already locked">Ce fichier est déjà verrouillé</string>
<string id="This file is not locked">Ce fichier n'est pas verrouillé</string>
<string id="Warning! A new version of this file is waiting to be validate. If you unlock this file, this version will be deleted!">Attention! Une nouvelle version de ce fichier est en attente de validation. Si vous déverrouiller le fichier, la version sera supprimée</string>
<string id="New major version?">Nouvelle version majeure?</string>
<string id="Confirm file">Confirmer le fichier</string>
<string id="Hour">Heure</string>
<string id="Clean log">Purger le log</string>
<string id="Clean all log entries before a given date">Supprimer toutes les entrées antérieures à la date suivante</string>
<string id="About your file">A propos de votre fichier</string>
<string id="Waiting to be validate">En attente de validation</string>
<string id="A new version file is waiting for you">Une version nouvelle du fichier est en attente</string>
<string id="A new version file has been uploaded">Une nouvelle version du fichier a été chargée</string>
<string id="Refused by ">Réfusée par </string>
<string id="Your new file version has been refused">Votre nouvelle version du fichier a été refusée</string>
<string id="Your new file version has been accepted">Votre nouvelle version du fichier a été acceptée</string>
<string id="File deleted">Fichier supprimé</string>
<string id="View log">Voir le log</string>
<string id="Change group">Changer de groupe</string>
<string id="Delegation">Délégation</string>
<string id="Currently you administer ">Vous administrez </string>
<string id="all site">tout le site</string>
<string id="Delegation group">Groupe de délégation</string>
<string id="Are you sure you want to delete this group and all its objects">Etes-vous sûr de vouloir supprimer ce groupe et tous ses objets</string>
<string id="WARNING: This group is used for delegation of administration. You can delete this group and all objects owned by this group. Or attach those objects to all site">ATTENTION: Ce groupe est utilisé par la délégation d'administration. Vous pouvez supprimer le groupe et ses objets. Ou seulement le groupe et, dans ce cas, ses objets seront attachés à tout le site</string>
<string id="Delete all">Supprimer tout</string>
<string id="Delete only group">Supprimer seulement le groupe</string>
<string id="Vacation managers">Gestionnaires de congés</string>
<string id="New manager">Nouveau gestionnaire</string>
<string id="List of vacations managers">Liste des Gestionnaires de congés</string>
<string id="Managers">Gestionnaires</string>
<string id="WARNING: This operation will delete group and all references">ATTENTION: Cette opération supprime le groupe et ses références</string>
<string id="Delete delegation">Supprimer la délégation</string>
<string id="Members of delegation group">Les membres du groupe de délégation</string>
<string id="Modify delegation">Modifier une délégation</string>
<string id="Create delegation">Créer une délégation</string>
<string id="Delegations list">Liste des délégations</string>
<string id="Modify approbation schema">Modifier un schéma d'approbation</string>
<string id="Create a new approbation schema">Créer un schéma d'approbation</string>
<string id="Test an approbation schema">Tester un schéma d'approbation</string>
<string id="Approbation schemas list">Liste des schémas d'approbation</string>
<string id="Your list has been updated">Votre liste a été mise à jour</string>
<string id="All site">Tout le site</string>
<string id="Change administration group">Changer de groupe d'Administration</string>
<string id="Article's model">Modèle d'article</string>
<string id="Display template">Patron d'affichage</string>
<string id="Optional">Optionnel</string>
<string id="Optional(fem)">Optionnelle</string>
<string id="Number of topics categories">Nombre de catégories de thèmes</string>
<string id="Top">Début</string>
<string id="Order a topic category">Ordonner les catégories de sujets</string>
<string id="Nickname contains blanc characters">L'identifiant contient des caractères blancs</string>
<string id="Alt">Alt</string>
<string id="Horizontal spacing">Espacement horizontal</string>
<string id="Vertical spacing">Espacement vertical</string>
<string id="Border">Bordure</string>
<string id="You must specify a number">Vous devez spécifier un nombre</string>
<string id="Optional sections list">Liste des sections optionnelles</string>
<string id="Template">Patron</string>
<string id="Section template">Patron de section</string>
<string id="Topics category parent">Catégorie de sujet parent</string>
<string id="Group calendar">Calendrier de groupe</string>
<string id="Personal calendar">Agenda personnel</string>
<string id="Allow user update personnal information">Permettre de mettre à jour les informations personnelles</string>
<string id="Create event category">Créer une catégorie d'évènement</string>
<string id="Event categories list">Liste des catégories d'évènements</string>
<string id="Update personnal informations">Mettre à jour les informations personnelles</string>
<string id="Update nickname">Mettre à jour le pseudonyme</string>
<string id="The maximum number of authorized optional sections was reached">Le nombre maximum de sections optionnelles autorisées a été atteint</string>
<string id="New documents">Nouveaux documents</string>
<string id="one day">une journée</string>
<string id="one week">une semaine</string>
<string id="one month">un mois</string>
<string id="one year">une année</string>
<string id="unlimited">illimité</string>
<string id="Remmember my login">Mémoriser mon identité sur cet ordinateur</string>
<string id="Waiting files">Fichiers en attente</string>
<string id="New Articles">Nouveaux articles</string>
<string id="Section disabled">Section désactivée</string>
<string id="Section enabled">Section activée</string>
<string id="Results">Résultats</string>
<string id="or">ou</string>
<string id="and">et</string>
<string id="exclude">exclure</string>
<string id="Please check your date format">Vérifier le format de la date</string>
<string id="after date">après la date</string>
<string id="before date">avant la date</string>
<string id="Middle">Milieu</string>
<string id="Absolute middle">Milieu absolu</string>
<string id="top">Haut</string>
<string id="Bottom">Bas</string>
<string id="Center">Centre</string>
<string id="Articles's authors can restrict access to articles">Les auteurs peuvent restreindre l'accès aux articles</string>
<string id="WARNING! Some articles uses access restriction. Changing access topic can make them inaccessible">ATTENTION! certains articles utilisent la restriction. Les changer de thèmes pourrais les rendre inaccessibles</string>
<string id="User name composition">Composition du nom d'utilisateur</string>
<string id="User can modifiy his nickname">L'utilisateur peut modifier sont identifiant</string>
<string id="User can modifiy his password">L'utilisateur peut modifier sont mot de passe</string>
<string id="Automatic connection">Connexion automatique</string>
<string id="Site slogan">Slogan du site</string>
<string id="Upload path">Répertoire d'upload</string>
<string id="File manager max file size">Taille maximum d'un fichier du gestionnaire de fichiers</string>
<string id="File manager max group directory size">Espace maximum occupé par un répertoire groupe</string>
<string id="File manager max user directory size">Espace maximum occupé par un répertoire utilisteur</string>
<string id="File manager max total size">Espace maximum occupé par le gestionnaire de fichiers</string>
<string id="ERROR: You must provide all file manager size limits !!">ERREUR : vous devez fournir toutes les tailles limites pour le gestionnaire de fichiers !!</string>
<string id="Access restriction">Restriction d'accès</string>
<string id="Are you sure you want to delete this event category">Voulez-vous vraiment effacer cette catégorie d'évenement</string>
<string id="Delete event category">Effacer la catégorie d'évenement</string>
<string id="Operator">Operateur</string>
<string id="And">Et</string>
<string id="No restriction">Pas de restriction</string>
<string id="This article uses the access restriction. Its displacement towards another topic can make it inaccessible">Cet article utilise la restriction  d\'accès, sont déplacement vers un autre thème peut le rendre inaccessible</string>
<string id="Update done">Mise à jour effetuée</string>
<string id="Advanced search">Recherche avancée</string>
<string id="Pages">Pages</string>
<string id="Popup">Popup</string>
<string id="Last update">Dernière mise à jour</string>
<string id="Messages to display per screen">Messages à afficher par écrans</string>
<string id="Create an e-mail account">Crée un compte e-mail</string>
<string id="popup">popup</string>
<string id="The new version need to be installed">La nouvelle version de l'add-on n'est pas installée</string>
<string id="Delegation">Délégation</string>
<string id="Modify delegation group">Modifier un groupe de délégation</string>
<string id="Are you sure you want to delete this delegation group">Etes-vous certain de vouloir détruire ce groupe de délégation</string>
<string id="WARNING: This operation will delete delegation group and all references">ATTENTION: Cette opération supprime le groupe de délégation et ses références</string>
<string id="This delegation group already exists">Ce groupe de délégation existe déja</string>
<string id="Group of delegation with the same name already exists!">Un groupe de délégation avec le même nom existe déja</string>
<string id="Managing administrators">Administrateurs délégués</string>
<string id="It is necessary to remove all associations with the users groups">Il est nécessaire d\'enlever toutes les associations avec les groupes utilisteurs</string>
<string id="Administrators of delegation">Les administrateurs de la délégation</string>
<string id="Managed groups">Groupes administrés</string>
<string id="Change administration">Changer d'administration</string>
<string id="Deputy functions">Fonctions déléguées</string>
<string id="Name to use for notification emails">Nom à utiliser pour les emails de notifications</string>
<string id="Number of results in research">Nombre de résultats dans la recherche</string>
<string id="A folder with the same name already exists">Un répertoire avec le même nom existe déja</string>
<string id="Do you really whant to delete this directory">Voulez-vous vraiment effacer ce répertoire</string>
<string id="E-mail password">Envoyer le mot de passe par e-mail</string>
</fr>